[
    {
        "productionTime": "2021-11-12 16:03:04.998611",
        "category": "Good",
        "count": 1,
        "qualityCode": "1"
    },
    {
        "productionTime": "2021-11-12 16:06:08.102417",
        "category": "Good",
        "count": 1,
        "qualityCode": "1"
    },
    {
        "productionTime": "2021-11-12 16:10:32.966394",
        "category": "Good",
        "count": 1,
        "qualityCode": "1"
    },
    {
        "productionTime": "2021-11-12 16:14:09.356447",
        "category": "Good",
        "count": 1,
        "qualityCode": "1"
    },
    {
        "productionTime": "2021-11-12 16:17:17.006574",
        "category": "Good",
        "count": 1,
        "qualityCode": "1"
    },
    {
        "productionTime": "2021-11-12 16:20:35.554095",
        "category": "Good",
        "count": 1,
        "qualityCode": "1"
    },
    {
        "productionTime": "2021-11-12 16:23:39.359738",
        "category": "Good",
        "count": 1,
        "qualityCode": "1"
    },
    {
        "productionTime": "2021-11-12 16:26:40.904311",
        "category": "Good",
        "count": 1,
        "qualityCode": "1"
    },
    {
        "productionTime": "2021-11-12 16:34:18.375100",
        "category": "Good",
        "count": 1,
        "qualityCode": "1"
    },
    {
        "productionTime": "2021-11-12 17:10:20.701305",
        "category": "Good",
        "count": 1,
        "qualityCode": "1"
    },
    {
        "productionTime": "2021-11-12 17:13:25.195776",
        "category": "Good",
        "count": 1,
        "qualityCode": "1"
    },
    {
        "productionTime": "2021-11-12 17:17:10.192424",
        "category": "Good",
        "count": 1,
        "qualityCode": "1"
    },
    {
        "productionTime": "2021-11-12 18:07:11.151845",
        "category": "Good",
        "count": 1,
        "qualityCode": "1"
    },
    {
        "productionTime": "2021-11-12 18:10:12.230382",
        "category": "Good",
        "count": 1,
        "qualityCode": "1"
    },
    {
        "productionTime": "2021-11-12 18:13:16.297100",
        "category": "Good",
        "count": 1,
        "qualityCode": "1"
    },
    {
        "productionTime": "2021-11-12 18:16:20.577050",
        "category": "Good",
        "count": 1,
        "qualityCode": "1"
    },
    {
        "productionTime": "2021-11-12 18:19:24.529903",
        "category": "Good",
        "count": 1,
        "qualityCode": "1"
    },
    {
        "productionTime": "2021-11-12 18:22:28.974007",
        "category": "Good",
        "count": 1,
        "qualityCode": "1"
    },
    {
        "productionTime": "2021-11-12 18:25:32.232947",
        "category": "Good",
        "count": 1,
        "qualityCode": "1"
    },
    {
        "productionTime": "2021-11-12 18:28:36.543458",
        "category": "Good",
        "count": 1,
        "qualityCode": "1"
    },
    {
        "productionTime": "2021-11-12 18:31:36.214667",
        "category": "Good",
        "count": 1,
        "qualityCode": "1"
    },
    {
        "productionTime": "2021-11-12 18:34:40.132778",
        "category": "Good",
        "count": 1,
        "qualityCode": "1"
    },
    {
        "productionTime": "2021-11-12 18:37:45.988100",
        "category": "Good",
        "count": 1,
        "qualityCode": "1"
    },
    {
        "productionTime": "2021-11-12 18:40:49.839276",
        "category": "Good",
        "count": 1,
        "qualityCode": "1"
    },
    {
        "productionTime": "2021-11-12 18:43:54.134735",
        "category": "Good",
        "count": 1,
        "qualityCode": "1"
    },
    {
        "productionTime": "2021-11-12 18:46:58.037042",
        "category": "Good",
        "count": 1,
        "qualityCode": "1"
    },
    {
        "productionTime": "2021-11-12 19:12:56.019400",
        "category": "Good",
        "count": 1,
        "qualityCode": "1"
    },
    {
        "productionTime": "2021-11-12 19:16:00.513449",
        "category": "Good",
        "count": 1,
        "qualityCode": "1"
    },
    {
        "productionTime": "2021-11-12 19:19:05.050189",
        "category": "Good",
        "count": 1,
        "qualityCode": "1"
    },
    {
        "productionTime": "2021-11-12 19:22:09.489547",
        "category": "Good",
        "count": 1,
        "qualityCode": "1"
    },
    {
        "productionTime": "2021-11-12 19:25:13.821276",
        "category": "Good",
        "count": 1,
        "qualityCode": "1"
    },
    {
        "productionTime": "2021-11-12 19:28:13.090057",
        "category": "Good",
        "count": 1,
        "qualityCode": "1"
    },
    {
        "productionTime": "2021-11-12 19:31:17.362999",
        "category": "Good",
        "count": 1,
        "qualityCode": "1"
    },
    {
        "productionTime": "2021-11-12 19:34:20.939769",
        "category": "Good",
        "count": 1,
        "qualityCode": "1"
    },
    {
        "productionTime": "2021-11-12 19:37:25.210459",
        "category": "Good",
        "count": 1,
        "qualityCode": "1"
    },
    {
        "productionTime": "2021-11-12 19:40:29.639486",
        "category": "Good",
        "count": 1,
        "qualityCode": "1"
    },
    {
        "productionTime": "2021-11-12 19:43:33.525804",
        "category": "Good",
        "count": 1,
        "qualityCode": "1"
    },
    {
        "productionTime": "2021-11-12 19:46:37.133655",
        "category": "Good",
        "count": 1,
        "qualityCode": "1"
    },
    {
        "productionTime": "2021-11-12 19:49:40.931129",
        "category": "Good",
        "count": 1,
        "qualityCode": "1"
    },
    {
        "productionTime": "2021-11-12 23:07:02.009001",
        "category": "Good",
        "count": 1,
        "qualityCode": "1"
    },
    {
        "productionTime": "2021-11-12 23:10:02.295617",
        "category": "Good",
        "count": 1,
        "qualityCode": "1"
    },
    {
        "productionTime": "2021-11-12 23:13:06.037926",
        "category": "Good",
        "count": 1,
        "qualityCode": "1"
    },
    {
        "productionTime": "2021-11-12 23:16:11.122403",
        "category": "Good",
        "count": 1,
        "qualityCode": "1"
    },
    {
        "productionTime": "2021-11-12 23:19:11.035611",
        "category": "Good",
        "count": 1,
        "qualityCode": "1"
    },
    {
        "productionTime": "2021-11-12 23:22:14.616839",
        "category": "Good",
        "count": 1,
        "qualityCode": "1"
    },
    {
        "productionTime": "2021-11-12 23:25:17.394307",
        "category": "Good",
        "count": 1,
        "qualityCode": "1"
    },
    {
        "productionTime": "2021-11-12 23:28:21.048113",
        "category": "Good",
        "count": 1,
        "qualityCode": "1"
    }
]